goes2repro/__init__.py
goes2repro/main.py
goes2repro-1.0.1.dist-info/LICENSE
goes2repro-1.0.1.dist-info/METADATA
goes2repro-1.0.1.dist-info/WHEEL
goes2repro-1.0.1.dist-info/entry_points.txt
goes2repro-1.0.1.dist-info/top_level.txt
goes2repro-1.0.1.dist-info/RECORD
