Metadata-Version: 2.1
Name: goes2repro
Version: 1.0.1
Summary: A package to download and process GOES-16/17 data
Home-page: https://github.com/helvecioneto/goes2repro
Author: Helvecio B. L. Neto
Author-email: helvecioblneto@gmail.com
License: LICENSE
Classifier: Programming Language :: Python
Classifier: Development Status :: 5 - Production/Stable
Classifier: Operating System :: OS Independent
Classifier: Programming Language :: Python :: 3.10
Classifier: Programming Language :: Python :: 3.11
Classifier: Programming Language :: Python :: 3.12
Classifier: Topic :: Scientific/Engineering
Classifier: Topic :: Software Development
Classifier: Topic :: Utilities
License-File: LICENSE
Requires-Dist: pandas
Requires-Dist: tqdm
Requires-Dist: s3fs
Requires-Dist: xarray
Requires-Dist: rioxarray
Requires-Dist: pyproj
Requires-Dist: goes2go
